pytracking_cdm/__init__.py
pytracking_cdm/cost_matrix.py
pytracking_cdm/distance_matrix.py
pytracking_cdm/pytracking_cdm.py
pytracking_cdm/sequencer.py
pytracking_cdm-0.2.0.dist-info/LICENSE
pytracking_cdm-0.2.0.dist-info/METADATA
pytracking_cdm-0.2.0.dist-info/WHEEL
pytracking_cdm-0.2.0.dist-info/RECORD
