Metadata-Version: 2.1
Name: pytracking-cdm
Version: 0.2.0
Summary: Processing eyetracking data for sequence analysis
Home-page: https://github.com/LS-Shikano/pytracking_cdm
License: MIT
Author: University of Konstanz - Center for Data and Methods
Requires-Python: >=3.10,<3.12
Classifier: License :: OSI Approved :: MIT License
Classifier: Programming Language :: Python :: 3
Classifier: Programming Language :: Python :: 3.10
Classifier: Programming Language :: Python :: 3.11
Requires-Dist: levenshtein (>=0.23.0,<0.24.0)
Requires-Dist: numpy (>=1.24.3,<2.0.0)
Requires-Dist: pandas (>=2.0.1,<3.0.0)
Requires-Dist: scipy (>=1.10.1,<2.0.0)
Requires-Dist: tqdm (>=4.66.1,<5.0.0)
Requires-Dist: weighted-levenshtein (>=0.2.2,<0.3.0)
Project-URL: Repository, https://github.com/LS-Shikano/pytracking_cdm
